veld/__init__.py
veld/__main__.py
veld/__version__.py
veld/exceptions.py
veld/stream_processor.py
veld/utils.py
veld/console/__init__.py
veld/console/application.py
veld/console/commands/__init__.py
veld/console/commands/_base.py
veld/console/commands/_plot.py
veld/console/commands/_reducable.py
veld/console/commands/_shared_docs.py
veld/console/commands/barcount.py
veld/console/commands/comparison.py
veld/console/commands/count.py
veld/console/commands/cumsum.py
veld/console/commands/frequency.py
veld/console/commands/histogram.py
veld/console/commands/lines.py
veld/console/commands/log.py
veld/console/commands/math.py
veld/console/commands/max.py
veld/console/commands/mean.py
veld/console/commands/median.py
veld/console/commands/min.py
veld/console/commands/mode.py
veld/console/commands/paired_ttest.py
veld/console/commands/passthrough.py
veld/console/commands/product.py
veld/console/commands/quantile.py
veld/console/commands/round.py
veld/console/commands/scatter.py
veld/console/commands/stdev.py
veld/console/commands/sum.py
veld/console/commands/summary.py
veld/console/commands/trimmed_mean.py
veld/console/commands/variance.py
veld/core/__init__.py
veld/core/betain.py
veld/core/cumsum.py
veld/core/frequency.py
veld/core/streamed_variance.py
veld/core/trimmed_mean.py
veld/core/operators/__init__.py
veld/core/operators/_base.py
veld/core/operators/_container.py
veld/core/operators/_wrapper.py
veld/core/operators/count.py
veld/core/operators/max.py
veld/core/operators/mean.py
veld/core/operators/median.py
veld/core/operators/min.py
veld/core/operators/mode.py
veld/core/operators/product.py
veld/core/operators/sum.py
veld/core/operators/summary.py
veld-0.1.5.data/data/man/man1/veld-add.1
veld-0.1.5.data/data/man/man1/veld-barcount.1
veld-0.1.5.data/data/man/man1/veld-count.1
veld-0.1.5.data/data/man/man1/veld-cumsum.1
veld-0.1.5.data/data/man/man1/veld-divide.1
veld-0.1.5.data/data/man/man1/veld-eq.1
veld-0.1.5.data/data/man/man1/veld-frequency.1
veld-0.1.5.dist-info/LICENSE
veld-0.1.5.dist-info/METADATA
veld-0.1.5.dist-info/WHEEL
veld-0.1.5.dist-info/entry_points.txt
veld-0.1.5.dist-info/top_level.txt
veld-0.1.5.dist-info/RECORD
