Metadata-Version: 2.1
Name: veld
Version: 0.1.5
Summary: A suite of tools for command line analytics
Home-page: https://github.com/GjjvdBurg/veld
Author: Gertjan van den Burg
Author-email: gertjanvandenburg@gmail.com
License: MIT
Classifier: License :: OSI Approved :: MIT License
Classifier: Programming Language :: Python
Classifier: Programming Language :: Python :: 3
Classifier: Programming Language :: Python :: 3.6
Classifier: Programming Language :: Python :: Implementation :: CPython
Classifier: Programming Language :: Python :: Implementation :: PyPy
Requires-Python: >=3.6.0
License-File: LICENSE
Requires-Dist: matplotlib >=3.3.4
Requires-Dist: numpy >=1.19
Requires-Dist: wilderness >=0.1.7
Provides-Extra: dev
Requires-Dist: mypy ; extra == 'dev'
Requires-Dist: green ; extra == 'dev'
Requires-Dist: pytest ; extra == 'dev'
Provides-Extra: docs
Provides-Extra: tests
Requires-Dist: mypy ; extra == 'tests'
Requires-Dist: green ; extra == 'tests'
Requires-Dist: pytest ; extra == 'tests'
